setup.py
AIJIcossh.egg-info/PKG-INFO
AIJIcossh.egg-info/SOURCES.txt
AIJIcossh.egg-info/dependency_links.txt
AIJIcossh.egg-info/requires.txt
AIJIcossh.egg-info/top_level.txt
cossh/__init__.py
cossh/python.py
cossh/telecontrol.py
cossh/yum.py