Metadata-Version: 1.0
Name: AIJIcossh
Version: 0.0.3
Summary: An ssh telecontrol Class for CentOS based on pxssh
Home-page: https://github.com/AIJIJI/cossh
Author: AIJI
Author-email: thecrazyaiji@gmail.com
License: UNKNOWN
Platform: UNKNOWN
